{
  "name": "SD Intake",
  "nodes": [
    {
      "parameters": {
        "content": "## SD Intake\n\nThin workflow — logic in lib/",
        "height": 140,
        "width": 360
      },
      "id": "28d9e870-1b0c-4d07-9ec0-3a0a67603a63",
      "name": "Sticky Note",
      "type": "n8n-nodes-base.stickyNote",
      "typeVersion": 1,
      "position": [
        -80,
        -120
      ]
    },
    {
      "parameters": {},
      "id": "f6a1b049-64a7-493a-a424-b79614efaf81",
      "name": "Manual Trigger",
      "type": "n8n-nodes-base.manualTrigger",
      "typeVersion": 1,
      "position": [
        0,
        0
      ]
    },
    {
      "parameters": {
        "mode": "runOnceForAllItems",
        "jsCode": "const path = await import('node:path');\nconst { pathToFileURL } = await import('node:url');\nconst repoRoot = process.env.N8N_REPO_ROOT ?? 'C:/repos/sandbox-n8n';\nconst dataRoot = process.env.N8N_DATA_ROOT ?? 'C:/sandbox-dir/sandbox-n8n';\nconst lib = await import(pathToFileURL(path.join(repoRoot, 'lib', 'index.js')).href);\nconst fs = await import('node:fs');\nconst { normalizeTicketPayload } = lib;\nconst raw = JSON.parse(fs.readFileSync(path.join(repoRoot, 'fixtures', 'servicedesk', 'tickets', 'vague-vpn.json'), 'utf8'));\nreturn [{ json: normalizeTicketPayload(raw) }];"
      },
      "id": "7a46342a-73a7-4c7d-901a-829655c306e5",
      "name": "Run lib",
      "type": "n8n-nodes-base.code",
      "typeVersion": 2,
      "position": [
        260,
        0
      ]
    }
  ],
  "connections": {
    "Manual Trigger": {
      "main": [
        [
          {
            "node": "Run lib",
            "type": "main",
            "index": 0
          }
        ]
      ]
    }
  },
  "active": false,
  "settings": {
    "executionOrder": "v1"
  },
  "versionId": "sd-intake",
  "meta": {
    "instanceId": "sandbox-n8n"
  },
  "tags": [
    "servicedesk"
  ]
}